{"bltb377ab306d29e646":{"stackHeaders":{"api_key":"<api_key>","branch":"main"},"urlPath":"/environments/preview","urls":[{"url":"","locale":"en"},{"url":"","locale":"fr"},{"url":"","locale":"de"},{"url":"","locale":"es"}],"name":"preview","_version":1,"uid":"bltb377ab306d29e646","created_at":"2024-03-14T06:57:13.874Z","updated_at":"2024-07-26T10:23:41.890Z"},"bltb73a6fe374802283":{"stackHeaders":{"api_key":"<api_key>","branch":"main"},"urlPath":"/environments/production","urls":[{"url":"","locale":"en"},{"url":"","locale":"fr"},{"url":"","locale":"de"},{"url":"","locale":"es"}],"name":"production","_version":1,"uid":"bltb73a6fe374802283","created_at":"2024-03-14T06:57:13.891Z","updated_at":"2024-06-20T08:38:51.137Z"}}